yapdict/VERSION.txt
yapdict/__init__.py
yapdict/yapdict.py
yapdict-0.0.0.dist-info/DESCRIPTION.rst
yapdict-0.0.0.dist-info/METADATA
yapdict-0.0.0.dist-info/RECORD
yapdict-0.0.0.dist-info/WHEEL
yapdict-0.0.0.dist-info/metadata.json
yapdict-0.0.0.dist-info/top_level.txt
