Metadata-Version: 2.0
Name: yapdict
Version: 0.0.0
Summary: Yet Another Persistent Dict: sqlite-backed storage with a Python dict API.
Home-page: https://github.com/brianjpetersen/yapdict
Author: Brian J Petersen
Author-email: brianjpetersen@gmail.com
License: MIT
Platform: UNKNOWN
Classifier: License :: OSI Approved :: MIT License
Classifier: Programming Language :: Python
Classifier: Programming Language :: Python :: 3.6
Classifier: Programming Language :: Python :: Implementation :: CPython
Requires-Dist: apsw (>=3.9.2-r1)
